beetsplug/api.py
beetsplug/audible.py
beetsplug/book.py
beetsplug/goodreads.py
beets_audible-1.2.1.dist-info/WHEEL
beets_audible-1.2.1.dist-info/METADATA
beets_audible-1.2.1.dist-info/RECORD
