Metadata-Version: 2.3
Name: beets-audible
Version: 1.2.1
Summary: Beets plugin for audiobook management
Keywords: beets,audible
Author: Dickson Tan
Author-email: Dickson Tan <dickson.tan.2013@gmail.com>
Classifier: Development Status :: 5 - Production/Stable
Classifier: Topic :: Multimedia :: Sound/Audio
Classifier: Topic :: Multimedia :: Sound/Audio :: Players :: MP3
Classifier: Environment :: Console
Classifier: License :: OSI Approved :: MIT License
Classifier: Programming Language :: Python :: 3
Classifier: Programming Language :: Python :: 3.8
Classifier: Programming Language :: Python :: 3.9
Classifier: Programming Language :: Python :: 3.10
Classifier: Programming Language :: Python :: 3.11
Classifier: Programming Language :: Python :: 3.12
Classifier: Programming Language :: Python :: Implementation :: CPython
Requires-Dist: beets>=2.5,<2.6
Requires-Dist: markdownify>=1,<2
Requires-Dist: natsort>=8,<9
Requires-Dist: tldextract>=5,<6
Requires-Dist: pytest ; extra == 'dev'
Requires-Dist: ruff==0.14.5 ; extra == 'dev'
Requires-Python: >=3.9
Project-URL: Changelog, https://github.com/Neurrone/beets-audible/blob/main/CHANGELOG.md
Project-URL: Documentation, https://github.com/Neurrone/beets-audible
Project-URL: Homepage, https://github.com/Neurrone/beets-audible
Project-URL: Issues, https://github.com/Neurrone/beets-audible/issues
Project-URL: Repository, https://github.com/Neurrone/beets-audible
Provides-Extra: dev
